__init__.py
gibberishpy/__init__.py
gibberishpy/_error.py
gibberishpy/scanner.py
gibberishpy-1.0.3.dist-info/METADATA
gibberishpy-1.0.3.dist-info/WHEEL
gibberishpy-1.0.3.dist-info/top_level.txt
gibberishpy-1.0.3.dist-info/RECORD
