Metadata-Version: 2.1
Name: gibberishpy
Version: 1.0.3
Summary: Using Markov chain to detect gibberish in text.
Author-email: Yuen Shing Yan Hindy <yuenshingyan@gmail.com>
Project-URL: Homepage, https://github.com/yuenshingyan/gibberishpy
Project-URL: Bug Tracker, https://github.com/yuenshingyan/gibberishpy/issues
Classifier: Programming Language :: Python :: 3
Classifier: License :: OSI Approved :: MIT License
Classifier: Operating System :: OS Independent
Requires-Python: >=3.10
